Workbook

Sheet Monthly sheet 
B1: AFRICAN GAMESKIN GROUP (PTY) LTD
B2: DATE: JUNE 2026
B4: SALES | G4: PURCHASES | K4: BANK:
B6: TURNOVER | D6: =+'Income Statement '!C4+'Income Statement '!C5 -> 8846029.9 | G6: HANNITAN - RECEIVED IN MONTH | K6: NEDBANK | L6: =+'Balance sheet '!C39 -> 2256051.8
B7: TURNOVER - EXPORTS | D7: =+'Income Statement '!C6 -> 759904.9 | G7: =+Hannitan!B44 -> 27484.3 | H7: M2 | K7: CFC | L7: =+'Balance sheet '!C40 -> 7388251.2
G8: =+Hannitan!D44 -> 6103468.1 | H8: VALUE EXCL VAT
D9: =SUM(D6:D8) -> 9605934.8 | G9: =+'Income Statement '!C13 -> 296994.04 | H9: 5% DISCOUNT
C10: M2 | G10: =+G8-G9 -> 5806474.1 | H10: TOTAL
B11: LEATHER SOLD: | C11: =+'Sales '!B39 -> 28111.71 | D11: =+'Sales '!C39 -> 9157383.6 | G11: =+G10/G7 -> 211.26512 | H11: AVERAGE PRICE | K11: LOAN ACCOUNTS
B12: AVERAGE SELLING PRICE: | C12: =+D11/C11 -> 325.74979
B13: LEATHER PURCHASED: | C13: =+G7+G15 -> 34761.64 | D13: =+G10+G16 -> 8319792 | G13: FUSION LEATHER - RECEIVED IN MONTH | K13: Spolden Inv | L13: 0
B14: AVERAGE PURCHASE PRICE : | C14: =D13/C13 -> 239.3383 | K14: Hildene Inv | L14: =+'Balance sheet '!C37 -> 1526847.6
G15: =+FLW!B37 -> 7277.34 | H15: M2 | L15: =SUM(L12:L14) -> 1526847.6
B16: SALES BREAKDOWN | G16: =+FLW!D37 -> 2513317.9 | H16: VALUE EXCL VAT
C17: June 2026 | D17: May 2026 | G17: =+G16/G15 -> 345.36217 | H17: AVERAGE PRICE
B18: Durban Branch | C18: =+'[1]Sales per Branch'!$T$6 -> 2362 | D18: 2702 | K18: INCOME STATEMENT JUNE 2026
B19: JHB Branch | C19: =+'[1]Sales per Branch'!$S$6 -> 9987 | D19: 9663 | G19: DEBTORS AGING AT END OF THE MONTH: | K19: TURNOVER | L19: 9592256.5
B20: Cape Town Branch | C20: =+'[1]Sales per Branch'!$R$6 -> 15762 | D20: 14573 | G20: CURRENT | H20: =+'Debtors '!F254 -> 5750509.5 | K20: COST OF SALES | L20: =+'Income Statement '!D10 -> 9049304
G21: 30DAYS | H21: =+'Debtors '!E254 -> 2659650.2 | K21: GROSS PROFIT | L21: =+L19-L20 -> 542952.45 | M21: =+L21/L19 -> 0.056603204
B22: Total m2 sold | C22: =SUM(C18:C21) -> 28111 | D22: =SUM(D18:D20) -> 26938 | G22: 60DAYS | H22: =+'Debtors '!D254 -> 339704.74 | K22: OTHER INCOME | L22: 397357.21
G23: 90DAYS | H23: =+'Debtors '!C254 -> 517460.73 | K23: EXPENSES | L23: 952854.61 | M23: =L23/L19 -> 0.099335814
B24: TOP 10 CUSTOMERS | C24: DM2 | D24: VALUE | G24: 120DAYS | H24: =+'Debtors '!B254 -> 233005.84 | K24: NET PROFIT | L24: =L21+L22-L23 -> -12544.95 | M24: =+L24/L19 -> -0.0013078205
B25: INSPIRE RENTALS PTY LTD | C25: 1648.56 | D25: 400521.1 | H25: =SUM(H20:H24) -> 9500331
B26: GH LEATHERS LTD | C26: 1464.08 | D26: 677878.46 | K26: INCOME STATEMENT YTD
B27: JULIANA DESIGNS (PTY) LTD | C27: 1244.83 | D27: 329879.95 | G27: CREDITORS AGING: | K27: TURNOVER | L27: 35799258
B28: COUCH POTATO | C28: 856.94 | D28: 213084.55 | G28: CURRENT | H28: =+'Suppliers '!G22 -> 3246489.7 | K28: COST OF SALES | L28: =+'Year to date'!D10 -> 32069257
B29: INYATHI LOUNGE (PTY) LTD | C29: 834.04 | D29: 202000.95 | G29: 30DAYS | H29: 0 | K29: GROSS PROFIT | L29: =L27-L28 -> 3730000.5 | M29: =+L29/L27 -> 0.10419212
B30: ALWAYS AROUND (PTY) LTD T/A BEESDAM | C30: 787.17 | D30: 221597.55 | G30: 60DAYS | H30: 0 | K30: OTHER INCOME | L30: 1275686.6
B31: LEATHER DIRECT (Pty) Ltd | C31: 722.42 | D31: 181422 | H31: =SUM(H28:H30) -> 3246489.7 | K31: EXPENSES | L31: 3831402.2 | M31: =L31/L27 -> 0.10702463
B32: ROWDY INTERNATIONAL (Pty) Ltd | C32: 707.48 | D32: 215960.95 | K32: NET PROFIT | L32: =L29+L30-L31 -> 1174284.9 | M32: =+L32/L27 -> 0.032801934
B33: LEATHER DIRECT (Pty) Ltd | C33: 597.6 | D33: 148022.8 | G33: STOCK | H33: =+M40 -> 28252762
B34: FF CLOTHING GROUP CC | C34: 583.21 | D34: 232642.6 | G34: DEBTORS | H34: =+H25 -> 9500331 | K34: STOCK - June 2026
L35: M2 | M35: VALUE
B36: Top 10 as % of total sales | C36: =+C48 -> 0.3360283 | G36: BANK | H36: =+L7+L6 -> 9644303 | K36: Cape Town | L36: =53708+18709 -> 72417 | M36: =13573047+6530769 -> 20103816
B37: CREDIT NOTES: 115 x CREDIT NOTES | C37: 5% of sales | D37: 512349.12 | G37: CREDITORS | H37: =-H31 -> -3246489.7 | K37: JHB | L37: =2632+23332+630 -> 26594 | M37: =920425+5013494+94500 -> 6028419
K38: Durban | L38: 3891.47 | M38: 999058.3
K39: Other | M39: =+[2]Gameskin!$F$53 -> 1121468.6
G40: TOTAL CURRENT ASSETS: | H40: =SUM(H33:H39) -> 44150906 | L40: TOTAL STOCK: | M40: =SUM(M36:M39) -> 28252762
D42: =+D37/D9 -> 0.053336727 | G42: Hannitan over deliveries
G44: Fusion delivered R700k in the last 3 days of the month
D46: =+D37/D9 -> 0.053336727
C47: =+C25+C26+C27+C28+C29+C30+C32+C31+C33+C34 -> 9446.33 | D47: =+D25+D26+D27+D28+D29+D30+D31+D32+D33+D34 -> 2823010.9
C48: =+C47/C11 -> 0.3360283 | D48: =+D47/D11 -> 0.30827702
D49: =+D37/D9 -> 0.053336727

Sheet Sheet1
A1: Purchase Items per Supplier : 01/06/2026 to 30/06/2026
B2: Qty | C2: Unit Cost | D2: Total
A3: Supplier : HAN001 - HANNITAN LEATHER CC
A4: Item : BWO001 - WOODLAND B PRINT SPICE | B4: 1703.95 | C4: 207 | D4: 352717.65
A5: Item : BWO002 - WOODLAND B PRINT TAN | B5: 2485.45 | C5: 207 | D5: 514488.15
A6: Item : CAP002 - CAPE BUFFALO COPPER | B6: 330.06 | C6: 274 | D6: 90436.44
A7: Item : DAY011 - DAYTONA TOFFEE | B7: 424.17 | C7: 292 | D7: 123857.64
A8: Item : ETO003 - ETOSHA CHESTNUT | B8: 600.25 | C8: 207 | D8: 124251.75
A9: Item : ETO007 - ETOSHA EMERALD | B9: 622.8 | C9: 207 | D9: 128919.6
A10: Item : IMP004 - IMPALA BLACK | B10: 573.96 | C10: 189 | D10: 108478.44
A11: Item : SOR001 - SORRENTO BLACK | B11: 1296.02 | C11: 178 | D11: 230691.56
A12: Item : SOR006 - SORRENTO COTTON WHITE | B12: 963.65 | C12: 178 | D12: 171529.7
A13: Item : SOR008 - SORRENTO CARAMEL | B13: 617.25 | C13: 178 | D13: 109870.5
A14: Item : SOR011 - SORRENTO COFFEE | B14: 1272.14 | C14: 178 | D14: 226440.92
A15: Item : WLS001 - WOODLAND BROWN B | B15: 1183.46 | C15: 207 | D15: 244976.22
... A17: Item : WLS003 - WOODLAND CHARCOAL B | B17: 615.31 | C17: 207 | D17: 127369.17
A18: Total for Supplier : HAN001 - HANNITAN LEATHER CC | B18: 13903.48
A19: GRAND TOTAL | D19: 2805534.8
D20: 201.78652

Sheet Balance sheet 
A1: AFRICAN GAMESKIN GROUP (PTY) LTD | Prepared by: African Gameskin
A2: BALANCE SHEET as at 30/06/2026
A4: EQUITY AND LIABILITIES
A5: Capital and Reserves
A7: Share Capital
B8: Members contribution | C8: 100 | D8: 100
A9: Retained Income
B10: Retained Income / (Accumulated Loss) | C10: 33130566
B11: Net Profit/Loss this year | C11: 1056454.4 | D11: 34187021 | E11: 34187121
A12: Shareholders Loan
B13: D Spolander | C13: -4072.66 | D13: -4072.66
A15: Minority Interest
A16: Non-current Liabilities
D17: -4072.66
D18: 34183048
A19: Current Liabilities
B20: Nedbank Credit Card | C20: 8954.5
B21: Garage Card - Control Account | C21: 55539.53
B22: Supplier Control Account | C22: 3246489.7
B23: Provision for Future Expenses | C23: 99554.51 | D23: 3410538.2 | E23: 3410538.2
A24: Total Equity and Liabilities | D24: 37593586
A26: ASSETS
A27: Non-current Assets
A29: Fixed Assets
B30: Motor Vehicles - Net Value | C30: 1438086.1
B31: Computer Equipment - Net Value | C31: 49169.98
B32: Furniture & Fittings - Net value | C32: 16195.62 | D32: 1503451.7 | E32: 1503451.7
A33: Current Assets
B34: Inventory
C35: Inventory | D35: 12760584
B36: Staff Loan | C36: 26632.2
B37: Hildene Investments (Pty) Ltd | C37: 1526847.6
B38: Customer Control Account | C38: 9499994.2
B39: Nedbank Cheque 1036 327663 | C39: 2256051.8
B40: USD Account 7095014132 | C40: 7388251.2
B41: Petty cash | C41: 8836.34
B42: Petty Cash | C42: 64927.84
B43: Sundry Customers | C43: 79748.41
B44: Taxation | C44: 2450142.8
B45: Vat / Tax Control Account | C45: 28118.29 | D45: 36090134 | E45: 36090134
A46: Total Assets | D46: 37593586

Sheet Income Statement 
A1: AFRICAN GAMESKIN GROUP (PTY) LTD | Prepared by: African Gameskin
A2: INCOME STATEMENT : 01/06/2026 to 30/06/2026
A3: SALES
B4: Sales | C4: 8793187
B5: Sales - other | C5: 52842.93
B6: Sales zero rated | C6: 759904.9 | D6: 9605934.8
A7: COST OF SALES
B8: Cost of Sales / Purchases | C8: 8837529
B9: Clearing and forwarding | C9: 28103.92
B10: Courier & Postage | C10: 183671.1 | D10: 9049304
A11: GROSS PROFIT / (LOSS) | C11: 556630.75
A12: OTHER INCOME
B13: Discount Received for Cash | C13: 296994.04
B14: Interest Received | C14: 12748.33
B15: Sundry Income | C15: 2977.76
B16: Foreign exchange Gain / Loss | C16: -2464.26 | D16: 310255.87
C17: 866886.62
A18: EXPENSES
B19: Accounting Fees | C19: 40125
B20: Advertising & Promotions | C20: 4620
B21: Bank Charges | C21: 2174.49
B22: Cleaning | C22: 4336.58
B23: Computer Expenses | C23: 1050.58
B24: Consumables | C24: 10494.2
B25: Credit card commission | C25: 10081.97
B26: Discount Allowed for Cash | C26: 779.7
B27: Electricity & Water | C27: 21886.74
B28: Insurance | C28: 29383.11
B29: Interest Paid | C29: 463.98
B30: Legal Fees | C30: 400
... B42: Telephone & Fax | C42: 14934.43
B43: Travel & Accommodation | C43: 18404.37 | D43: 997262.04
A44: NET PROFIT / (LOSS) BEFORE TAX | C44: -130375.42
A45: TAX
A46: DIVIDENDS
A47: NET PROFIT / (LOSS) | C47: -130375.42

Sheet Year to date
A1: AFRICAN GAMESKIN GROUP (PTY) LTD | Prepared by: African Gameskin
A2: INCOME STATEMENT : 01/03/2026 to 30/06/2026
A3: SALES
B4: Sales | C4: 34310959
B5: Sales - other | C5: 63941.41
B6: Sales zero rated | C6: 1438036.1 | D6: 35812936
A7: COST OF SALES
B8: Cost of Sales / Purchases | C8: 31231842
B9: Clearing and forwarding | C9: 182677.02
B10: Courier & Postage | C10: 654738.04 | D10: 32069257
A11: GROSS PROFIT / (LOSS) | C11: 3743678.8
A12: OTHER INCOME
B13: Discount Received for Cash | C13: 1039525.7
B14: Interest Received | C14: 40601.38
B15: Sundry Income | C15: 6271.17
B16: Foreign exchange Gain / Loss | C16: 102187 | D16: 1188585.2
C17: 4932264
A18: EXPENSES
B19: Accounting Fees | C19: 46454
B20: Advertising & Promotions | C20: 20245
B21: Bank Charges | C21: 42993.55
B22: Cleaning | C22: 21356.88
B23: Computer Expenses | C23: 9031.12
B24: Consumables | C24: 63147.37
B25: Consulting Fees | C25: 48961.29
B26: Credit card commission | C26: 46797.21
B27: Discount Allowed for Cash | C27: 1122.38
B28: Electricity & Water | C28: 84846.08
B29: Gifts | C29: 9129
B30: Insurance | C30: 113925.59
... B44: Telephone & Fax | C44: 57629.92
B45: Travel & Accommodation | C45: 122315.02 | D45: 3875809.6
A46: NET PROFIT / (LOSS) BEFORE TAX | C46: 1056454.4
A47: TAX
A48: DIVIDENDS
A49: NET PROFIT / (LOSS) | C49: 1056454.4

Sheet Debtors 
A1: AFRICAN GAMESKIN GROUP (PTY) LTD | Prepared by: African Gameskin
A2: Customer Age Analysis for Monthly Customers as at 30/06/2026
A3: Name | B3: 120+ Days | C3: 90 Days | D3: 60 Days | E3: 30 Days | F3: Current | G3: Total Due
A4: ABM002 - ABM UPHOLSTERERS | B4: 0 | C4: 0 | D4: 0 | E4: 0 | F4: -403.65 | G4: -403.65
A5: AFI001 - AFIKA PROMOTIONS | B5: 0 | C5: 282273.87 | D5: 7789.76 | E5: 128276.36 | F5: 211205.73 | G5: 629545.72
A6: AGD001 - A&G DESIGN | B6: 0 | C6: 0 | D6: 0 | E6: 0 | F6: -491.63 | G6: -491.63
A7: ALD003 - ALDORA MANUFACTURES | B7: 0 | C7: 0 | D7: 0 | E7: 0 | F7: 2594.4 | G7: 2594.4
A8: ALE003 - ALEXIOU LEATHER COUCHES | B8: 558.9 | C8: 30209 | D8: 12919.91 | E8: 5986.9 | F8: 25069.02 | G8: 74743.73
A9: ALW002 - ALWAYS AROUND (PTY) LTD T/A BEESDAM | B9: 0 | C9: 0 | D9: 0 | E9: 0 | F9: 162693.95 | G9: 162693.95
A10: ANG002 - ANGEL FOOTWEAR | B10: 0 | C10: 30491.74 | D10: 0 | E10: 0 | F10: 0 | G10: 30491.74
A11: ARL006 - ARLEV INVESTMENTS (PTY) LTD | B11: 0 | C11: 0 | D11: 0 | E11: 0 | F11: 44.91 | G11: 44.91
A12: ARN001 - ARNOLD SHOES | B12: 0 | C12: 0 | D12: 0 | E12: -187.91 | F12: 0 | G12: -187.91
A13: ARR002 - QUIVER TRUST T/A ARROW LEATHER GOODS | B13: 0 | C13: 0 | D13: 0 | E13: 0 | F13: 7769.04 | G13: 7769.04
A14: ASC001 - ASCOT UPHOLSTERY | B14: -2558 | C14: 0 | D14: 0 | E14: 0 | F14: 0 | G14: -2558
A15: BAO002 - BAO-BAGS | B15: 0 | C15: 0 | D15: 0 | E15: 0 | F15: 5083.34 | G15: 5083.34
... A254: Totals : | B254: 233005.84 | C254: 517460.73 | D254: 339704.74 | E254: 2659650.2 | F254: 5750509.5 | G254: 9500331
A255: PERCENTAGE : | B255: 2.45% | C255: 5.45% | D255: 3.58% | E255: 28.00% | F255: 60.53% | G255: 100.00%
A256: GRAND TOTALS : | G256: 9500331

Sheet Suppliers 
A1: AFRICAN GAMESKIN GROUP (PTY) LTD | Prepared by: African Gameskin
A2: Supplier Age Analysis as at 30/06/2026
A3: Name | B3: 120+ Days | C3: 90 Days | D3: 60 Days | E3: 30 Days | F3: Current | G3: Total Due
A4: C2M001 - C2M | B4: 0 | C4: 0 | D4: 0 | E4: 460 | F4: 46143.75 | G4: 46603.75
A5: CEZ001 - CEZ Investements | B5: 0 | C5: 0 | D5: 0 | E5: 0 | F5: -56198.37 | G5: -56198.37
A6: CIT002 - CITI - SPRINT EXPRESS COURIER | B6: 0 | C6: 0 | D6: 0 | E6: 0 | F6: 954.87 | G6: 954.87
A7: CLO001 - CLOUD LOGISTICS | B7: 0 | C7: 0 | D7: 0 | E7: 0 | F7: 32227.73 | G7: 32227.73
A8: COP001 - COPYWRITE BUSINESS CENTRE CC T/A | B8: 0 | C8: 0 | D8: 0 | E8: 0 | F8: 4403 | G8: 4403
A9: DPD001 - DPD LOGISTICS | B9: 0 | C9: 0 | D9: 0 | E9: 0 | F9: 12252.61 | G9: 12252.61
A10: FRE001 - FREIGHTMORE | B10: 0 | C10: 0 | D10: 0 | E10: 0 | F10: 127619.78 | G10: 127619.78
A11: HAN001 - HANNITAN LEATHER CC | B11: 0 | C11: 0 | D11: 0 | E11: 0 | F11: 55848.07 | G11: 55848.07
A12: HIL001 - HILDENE INVESTMENTS | B12: 0 | C12: 0 | D12: 0 | E12: 0 | F12: 11034.65 | G12: 11034.65
A13: OLI001 - OLIVETTI | B13: 0 | C13: 0 | D13: 0 | E13: 0 | F13: 1172.35 | G13: 1172.35
A14: SIY002 - SIYA BONGA | B14: 0 | C14: 0 | D14: 0 | E14: 0 | F14: 8330 | G14: 8330
A15: STE002 - STEINER HYGIENE | B15: 0 | C15: 0 | D15: 0 | E15: 0 | F15: -1.6 | G15: -1.6
... A22: TOTAL : | B22: 0 | C22: 0 | D22: 0 | E22: 460 | F22: 3246029.7 | G22: 3246489.7
A23: PERCENTAGE : | B23: 0.00% | C23: 0.00% | D23: 0.00% | E23: 0.01% | F23: 99.99% | G23: 100.00%
A24: GRAND TOTAL : | G24: 3246489.7

Sheet Sales 
A1: AFRICAN GAMESKIN GROUP (PTY) LTD | Prepared by: African Gameskin
A2: Sales by Inventory Category 01/06/2026 to 30/06/2026
B3: Qty | C3: Total Selling
A4: Category : 000 - None | B4: 299.99 | C4: 73439.4
A5: Category : 001 - Gazelle | B5: 1213.13 | C5: 435357.8
A6: Category : 002 - Woodland B JHB no print | B6: 2059.11 | C6: 534706.65
A7: Category : 003 - Cape Buffalo | B7: 179.29 | C7: 62956.45
A8: Category : 004 - Classic Collection | B8: 93.23 | C8: 33935.8
A9: Category : 005 - Nappa Collection | B9: 178.3 | C9: 62895.7
A10: Category : 007 - Santos / Sorrento | B10: 2215.51 | C10: 561768.82
A11: Category : 010 - Cow Suede Splits | B11: 433.61 | C11: 148790
A12: Category : 012 - Barcelona | B12: 1676.45 | C12: 702536.7
A13: Category : 013 - Fusion Stock Lot | B13: 506.46 | C13: 162766.75
A14: Category : 015 - Navada | B14: 42.22 | C14: 25263.5
A15: Category : 016 - Nova | B15: 172.06 | C15: 58545.3
... A38: Category : 051 - Antique | B38: 573.58 | C38: 149130.8
B39: =SUM(B4:B38) -> 28111.71 | C39: =SUM(C4:C38) -> 9157383.6
A40: Category : 057 - XX Skins - Zebra | B40: 1 | C40: 14000
A41: Category : 058 - XX - Skins - Cow hides | B41: 46.26 | C41: 140155
A42: Category : 059 - XX - Skins - Gameskin | B42: 480 | C42: 199366.4
A43: Category : 062 - XX - Transport | B43: 371.92 | C43: 44120.38
A44: Category : 067 - AGS Stock lot | B44: 2 | C44: 0
A45: GRAND TOTAL | B45: 29012.89 | C45: 9555025.4
C50: =+C39-'[1]Sales per month'!$D$73 -> -0.64
C51: 2066302.8

Sheet Invoices
A1: AFRICAN GAMESKIN GROUP (PTY) LTD | Prepared by: African Gameskin
A2: Sales Journal for period 01/06/2026 to 30/06/2026
A4: Customer | B4: Document | C4: Date | D4: Order | E4: Exclusive | F4: Tax | G4: Inclusive
A5: CANCEL | B5: Tax Invoice : 1 | C5: 15/06/2026
A6: CANCEL | B6: Tax Invoice : 2 | C6: 15/06/2026
A7: CANCEL | B7: Tax Invoice : 7 | C7: 15/06/2026
A8: OGU001 | B8: Credit Note : CR10683 | C8: 01/06/2026 | D8: INW50920 | E8: -3160 | F8: -474 | G8: -3634
A9: RUS003 | B9: Credit Note : CR10684 | C9: 01/06/2026 | D9: INW50981 | E9: -777.6 | F9: -116.64 | G9: -894.24
A10: WUN001 | B10: Credit Note : CR10686 | C10: 01/06/2026 | D10: VARIOUS | E10: -17656.4 | F10: -2648.46 | G10: -20304.86
A11: COV021 | B11: Credit Note : CR10690 | C11: 01/06/2026 | D11: INW50828 | E11: -1082.65 | F11: -162.4 | G11: -1245.05
A12: CAM003 | B12: Credit Note : CR10691 | C12: 01/06/2026 | D12: INW50294 | E12: -3404.25 | F12: -510.64 | G12: -3914.89
A13: OKH001 | B13: Credit Note : CR10692 | C13: 02/06/2026 | D13: INW51043 | E13: -2455.2 | F13: -368.28 | G13: -2823.48
A14: VIN006 | B14: Credit Note : CR10693 | C14: 02/06/2026 | D14: INW50765 | E14: -1718.2 | F14: -257.73 | G14: -1975.93
A15: NRH01 | B15: Credit Note : CR10694 | C15: 03/06/2026 | D15: INW50371 | E15: -3266.75 | F15: -490.01 | G15: -3756.76
A16: JUL003 | B16: Credit Note : CR10695 | C16: 03/06/2026 | D16: INW51155 | E16: -13435.5 | F16: -2015.33 | G16: -15450.83
A17: VAN020 | B17: Credit Note : CR10696 | C17: 03/06/2026 | D17: INW50832 | E17: -1201.2 | F17: -180.18 | G17: -1381.38
A18: NMB001 | B18: Credit Note : CR10697 | C18: 04/06/2026 | D18: INW50917 | E18: -3166.6 | F18: -474.99 | G18: -3641.59
A19: CASH | B19: Credit Note : CR10698 | C19: 04/06/2026 | D19: INW51168 | E19: -1756 | F19: -263.4 | G19: -2019.4
... A122: WUN001 | B122: Credit Note : CR10804 | C122: 29/06/2026 | D122: INW52046 | E122: -451.8 | F122: -67.77 | G122: -519.57
A123: GWO001 | B123: Tax Invoice : INW50859 | C123: 01/06/2026 | E123: 47328.3 | F123: 7099.25 | G123: 54427.55
A124: MOO008 | B124: Tax Invoice : INW50936 | C124: 01/06/2026 | E124: 4504 | F124: 675.6 | G124: 5179.6
A125: AARD01 | B125: Tax Invoice : INW50940 | C125: 02/06/2026 | E125: 2539.25 | F125: 380.89 | G125: 2920.14
A126: THE000 | B126: Tax Invoice : INW50984 | C126: 01/06/2026 | E126: 3954.95 | F126: 593.24 | G126: 4548.19
A127: STE018 | B127: Tax Invoice : INW50989 | C127: 01/06/2026 | E127: 1050 | F127: 157.5 | G127: 1207.5
A128: SIT003 | B128: Tax Invoice : INW51003 | C128: 01/06/2026 | E128: 3057.25 | F128: 458.59 | G128: 3515.84
A129: GUI001 | B129: Tax Invoice : INW51004 | C129: 01/06/2026 | E129: 16031.8 | F129: 2404.77 | G129: 18436.57
A130: NKA001 | B130: Tax Invoice : INW51005 | C130: 01/06/2026 | D130: ATT: NKANYISO | E130: 2940 | F130: 441 | G130: 3381
A131: HOP001 | B131: Tax Invoice : INW51006 | C131: 01/06/2026 | D131: PO: 15957 | E131: 24750 | F131: 3712.5 | G131: 28462.5
A132: BAR003 | B132: Tax Invoice : INW51007 | C132: 01/06/2026 | E132: 64195.4 | F132: 9629.31 | G132: 73824.71
A133: BAR003 | B133: Tax Invoice : INW51008 | C133: 01/06/2026 | E133: 6316.7 | F133: 947.51 | G133: 7264.21
A134: BRE003 | B134: Tax Invoice : INW51009 | C134: 01/06/2026 | D134: ATT: MICHELLE/ANGELA | E134: 30375 | F134: 4556.25 | G134: 34931.25
A135: SMI003 | B135: Tax Invoice : INW51010 | C135: 01/06/2026 | D135: ATT:PAM | E135: 700.35 | F135: 105.05 | G135: 805.4
A136: KUR001 | B136: Tax Invoice : INW51011 | C136: 01/06/2026 | E136: 1392.6 | F136: 208.89 | G136: 1601.49
A137: NAN003 | B137: Tax Invoice : INW51012 | C137: 01/06/2026 | E137: 4785.9 | F137: 717.89 | G137: 5503.79
A138: NAUD01 | B138: Tax Invoice : INW51013 | C138: 01/06/2026 | E138: 1542.83 | F138: 231.43 | G138: 1774.26
A139: SEA003 | B139: Tax Invoice : INW51014 | C139: 01/06/2026 | D139: ATT: ADAM | E139: 1668 | F139: 250.2 | G139: 1918.2
A140: MAZ002 | B140: Tax Invoice : INW51015 | C140: 01/06/2026 | E140: 3302.1 | F140: 495.32 | G140: 3797.42
A141: RED001 | B141: Tax Invoice : INW51016 | C141: 01/06/2026 | E141: 40000 | F141: 6000 | G141: 46000
A142: RED001 | B142: Tax Invoice : INW51017 | C142: 01/06/2026 | E142: 8403.75 | F142: 1260.56 | G142: 9664.31
A143: MEY001 | B143: Tax Invoice : INW51018 | C143: 01/06/2026 | D143: PO#MADELEINE | E143: 2861.25 | F143: 429.19 | G143: 3290.44
A144: TEN003 | B144: Tax Invoice : INW51019 | C144: 01/06/2026 | D144: ATT: CLARE | E144: 1668 | F144: 250.2 | G144: 1918.2
A145: LEA03 | B145: Tax Invoice : INW51020 | C145: 01/06/2026 | E145: 26192.8 | F145: 3928.92 | G145: 30121.72
A146: RUS001 | B146: Tax Invoice : INW51021 | C146: 01/06/2026 | E146: 5024.32 | F146: 753.67 | G146: 5777.99
A147: COU001 | B147: Tax Invoice : INW51022 | C147: 01/06/2026 | E147: 5907.6 | F147: 886.14 | G147: 6793.74
A148: BLU011 | B148: Tax Invoice : INW51023 | C148: 01/06/2026 | E148: 2564.7 | F148: 384.72 | G148: 2949.42
A149: ZUL004 | B149: Tax Invoice : INW51024 | C149: 01/06/2026 | E149: 3146.25 | F149: 471.94 | G149: 3618.19
A150: TRP001 | B150: Tax Invoice : INW51025 | C150: 01/06/2026 | E150: 25981.85 | F150: 3897.29 | G150: 29879.14
A151: ATH002 | B151: Tax Invoice : INW51026 | C151: 01/06/2026 | E151: 25395 | F151: 3809.25 | G151: 29204.25
A152: MOO008 | B152: Tax Invoice : INW51027 | C152: 01/06/2026 | E152: 707.05 | F152: 106.06 | G152: 813.11
A153: ZAL001 | B153: Tax Invoice : INW51028 | C153: 01/06/2026 | D153: ATT: SUE | E153: 1700 | F153: 255 | G153: 1955
A154: KZN001 | B154: Tax Invoice : INW51029 | C154: 01/06/2026 | D154: ATT: ANWAR | E154: 33537.47 | F154: 5030.62 | G154: 38568.09
A155: JUL003 | B155: Tax Invoice : INW51030 | C155: 01/06/2026 | E155: 29854.9 | F155: 4478.24 | G155: 34333.14
A156: FFUN01 | B156: Tax Invoice : INW51031 | C156: 01/06/2026 | E156: 13028.4 | F156: 1954.26 | G156: 14982.66
A157: CRE007 | B157: Tax Invoice : INW51032 | C157: 01/06/2026 | D157: ATT: ROWAN | E157: 4691.6 | F157: 703.74 | G157: 5395.34
A158: RUS003 | B158: Tax Invoice : INW51034 | C158: 01/06/2026 | E158: 928.8 | F158: 139.32 | G158: 1068.12
A159: RUS001 | B159: Tax Invoice : INW51035 | C159: 01/06/2026 | E159: 3334.07 | F159: 500.11 | G159: 3834.18
A160: GYP001 | B160: Tax Invoice : INW51036 | C160: 01/06/2026 | E160: 12711.9 | F160: 1906.79 | G160: 14618.69
A161: CASH | B161: Tax Invoice : INW51037 | C161: 01/06/2026 | D161: ATT: DEWALD | E161: 5000 | F161: 750 | G161: 5750
A162: FIO001 | B162: Tax Invoice : INW51038 | C162: 01/06/2026 | E162: 7017.6 | F162: 1052.64 | G162: 8070.24
A163: CAP003 | B163: Tax Invoice : INW51039 | C163: 01/06/2026 | E163: 2643.5 | F163: 396.53 | G163: 3040.03
A164: RIK001 | B164: Tax Invoice : INW51040 | C164: 01/06/2026 | E164: 2635.2 | F164: 395.28 | G164: 3030.48
A165: COA003 | B165: Tax Invoice : INW51041 | C165: 01/06/2026 | E165: 1543.8 | F165: 231.57 | G165: 1775.37
A166: HYD001 | B166: Tax Invoice : INW51042 | C166: 01/06/2026 | E166: 7171.35 | F166: 1075.7 | G166: 8247.05
A167: OKH001 | B167: Tax Invoice : INW51043 | C167: 01/06/2026 | D167: 6158_27 | E167: 2455.2 | F167: 368.28 | G167: 2823.48
A168: ILOV00 | B168: Tax Invoice : INW51044 | C168: 01/06/2026 | D168: ATT: DINGAAN | E168: 3751.8 | F168: 562.77 | G168: 4314.57
A169: LAR001 | B169: Tax Invoice : INW51045 | C169: 01/06/2026 | E169: 888.25 | F169: 133.24 | G169: 1021.49
A170: FRO001 | B170: Tax Invoice : INW51046 | C170: 01/06/2026 | D170: SOUTHERN SUPPLY | E170: 1216.6 | F170: 182.49 | G170: 1399.09
A171: HOU016 | B171: Tax Invoice : INW51047 | C171: 01/06/2026 | E171: 770.35 | F171: 115.55 | G171: 885.9
A172: H&T001 | B172: Tax Invoice : INW51048 | C172: 01/06/2026 | D172: PO# VAN NIEKERK | E172: 2149.2 | F172: 322.38 | G172: 2471.58
A173: LIZ007 | B173: Tax Invoice : INW51049 | C173: 01/06/2026 | E173: 2906.75 | F173: 436.01 | G173: 3342.76
A174: MAR064 | B174: Tax Invoice : INW51050 | C174: 01/06/2026 | E174: 935 | F174: 140.25 | G174: 1075.25
A175: SAZ001 | B175: Tax Invoice : INW51051 | C175: 01/06/2026 | E175: 678.05 | F175: 101.71 | G175: 779.76
A176: INS011 | B176: Tax Invoice : INW51052 | C176: 01/06/2026 | D176: 38823 | E176: 12621.6 | F176: 1893.24 | G176: 14514.84
A177: UVA011 | B177: Tax Invoice : INW51053 | C177: 01/06/2026 | E177: 3912.45 | F177: 586.87 | G177: 4499.32
A178: SEA003 | B178: Tax Invoice : INW51054 | C178: 01/06/2026 | D178: ATT: ADAM | E178: 3332.1 | F178: 499.82 | G178: 3831.92
A179: PIT002 | B179: Tax Invoice : INW51055 | C179: 01/06/2026 | D179: ATT: YASSEN | E179: 4790.25 | F179: 718.54 | G179: 5508.79
A180: CA001 | B180: Tax Invoice : INW51056 | C180: 01/06/2026 | E180: 3069.9 | F180: 460.49 | G180: 3530.39
A181: WLF001 | B181: Tax Invoice : INW51057 | C181: 01/06/2026 | E181: 860 | F181: 129 | G181: 989
A182: NOL006 | B182: Tax Invoice : INW51058 | C182: 01/06/2026 | E182: 1000 | F182: 150 | G182: 1150
A183: HAN00 | B183: Tax Invoice : INW51059 | C183: 01/06/2026 | E183: 450 | F183: 67.5 | G183: 517.5
A184: LUN006 | B184: Tax Invoice : INW51060 | C184: 01/06/2026 | E184: 2261.8 | F184: 339.28 | G184: 2601.08
A185: CES021 | B185: Tax Invoice : INW51062 | C185: 01/06/2026 | E185: 1581.15 | F185: 237.18 | G185: 1818.33
A186: BEAT01 | B186: Tax Invoice : INW51063 | C186: 01/06/2026 | E186: 20689.75 | F186: 3103.46 | G186: 23793.21
A187: NOV021 | B187: Tax Invoice : INW51064 | C187: 01/06/2026 | E187: 771.9 | F187: 115.79 | G187: 887.69
A188: FRA005 | B188: Tax Invoice : INW51065 | C188: 01/06/2026 | D188: ATT: BEN/HELGA/ANDRE | E188: 10959.4 | F188: 1643.91 | G188: 12603.31
A189: SKI002 | B189: Tax Invoice : INW51066 | C189: 01/06/2026 | D189: ATT: JAMES | E189: 3910.65 | F189: 586.6 | G189: 4497.25
A190: ASH004 | B190: Tax Invoice : INW51067 | C190: 01/06/2026 | E190: 16102.5 | F190: 2415.38 | G190: 18517.88
A191: NOL005 | B191: Tax Invoice : INW51068 | C191: 01/06/2026 | E191: 735.09 | F191: 110.26 | G191: 845.35
A192: BAO002 | B192: Tax Invoice : INW51069 | C192: 01/06/2026 | D192: ATT: BIANA | E192: 6284 | F192: 942.6 | G192: 7226.6
A193: BEU001 | B193: Tax Invoice : INW51070 | C193: 01/06/2026 | E193: 2390.84 | F193: 358.63 | G193: 2749.47
A194: NS002 | B194: Tax Invoice : INW51071 | C194: 01/06/2026 | D194: ATT: KEVIN | E194: 887.5 | F194: 133.13 | G194: 1020.63
A195: LON006 | B195: Tax Invoice : INW51072 | C195: 01/06/2026 | E195: 1720.05 | F195: 258.01 | G195: 1978.06
A196: KNA002 | B196: Tax Invoice : INW51073 | C196: 01/06/2026 | E196: 783.1 | F196: 117.47 | G196: 900.57
A197: KNA002 | B197: Tax Invoice : INW51074 | C197: 01/06/2026 | E197: 1307.9 | F197: 196.19 | G197: 1504.09
A198: BEL023 | B198: Tax Invoice : INW51075 | C198: 01/06/2026 | E198: 750.86 | F198: 112.63 | G198: 863.49
A199: DOU002 | B199: Tax Invoice : INW51076 | C199: 01/06/2026 | E199: 3752.19 | F199: 562.84 | G199: 4315.03
A200: DON009 | B200: Tax Invoice : INW51077 | C200: 01/06/2026 | D200: PO#26/06/240 | E200: 19351.5 | F200: 2902.73 | G200: 22254.23
A201: VER001 | B201: Tax Invoice : INW51078 | C201: 01/06/2026 | E201: 15664 | F201: 2349.6 | G201: 18013.6
A202: ZAB001 | B202: Tax Invoice : INW51079 | C202: 01/06/2026 | E202: 1551.6 | F202: 232.74 | G202: 1784.34
A203: HIG001 | B203: Tax Invoice : INW51080 | C203: 01/06/2026 | E203: 59640.6 | F203: 8946.09 | G203: 68586.69
...

Sheet Stock 

Sheet Per Customer 
A1: AFRICAN GAMESKIN GROUP (PTY) LTD | Prepared by: African Gameskin
A2: Sales by Customer 01/06/2026 to 30/06/2026
A3: Customer Code and Name | B3: Qty | C3: Total Selling
A4: BIR003 - BIRTHMARK INTERIORS | C4: 0
A5: COV021 - COVERFRESH UPHOLSTERY | C5: -128.45
A6: CUR009 - CURLICUE PTY LTD | C6: -32675.7
A7: DIAZ01 - DIAZ DESIGN | C7: -870.05
A8: NMB001 - NMB FURNITURE PTY (LTD) | C8: -1349
A9: NRH01 - NORTH HAMPTON LEATHER | C9: -135.05
A10: OFA004 - OFFROAD ALLEY | C10: 0
A11: OGU001 - OGUN OUTFITTERS | C11: -3160
A12: ORI001 - ORIGIN INTERIORS | C12: 0
A13: SPL001 - SPLITTING IMAGE TAXIDERMY | C13: -493
A14: WUN001 - WUNDERS FINE FURNISHINGS | C14: -15377.3
A15: XIL001 - Xilutsi Trading (Pty) Ltd | C15: 0
A16: INSPIRE RENTALS PTY LTD | B16: 1648.56 | C16: 400521.1 | D16: LM
A17: GH LEATHERS LTD | B17: 1464.08 | C17: 677878.46 | D17: Bianca
A18: JULIANA DESIGNS (PTY) LTD | B18: 1244.83 | C18: 329879.95 | D18: Savannah
A19: COUCH POTATO | B19: 856.94 | C19: 213084.55 | D19: Bianca
A20: INYATHI LOUNGE (PTY) LTD | B20: 834.04 | C20: 202000.95 | D20: Savannah
A21: ALWAYS AROUND (PTY) LTD T/A BEESDAM | B21: 787.17 | C21: 221597.55 | D21: Bianca
A22: LEATHER DIRECT (Pty) Ltd | B22: 722.42 | C22: 181422 | D22: Melani
A23: ROWDY INTERNATIONAL (Pty) Ltd | B23: 707.48 | C23: 215960.95 | D23: Melani
A24: LEATHER DIRECT (Pty) Ltd | B24: 597.6 | C24: 148022.8 | D24: Melani
A25: FF CLOTHING GROUP CC | B25: 583.21 | C25: 232642.6 | D25: Bianca
A26: BOOT & RALLY (PTY) (LTD) | B26: 543.53 | C26: 191245.82 | D26: LM
A27: AFIKA PROMOTIONS | B27: 459.86 | C27: 179935.3 | D27: Melani
... A39: VER001 - VERMONT LEATHER | B39: 249.89 | C39: 89177.9 | D39: LM
A40: CA001 - CASH CUSTOMERS | B40: 244.63 | C40: 88800.75
A41: AUV001 - AUVERGNE | B41: 229.86 | C41: 56315.7 | D41: Jordan
A42: RUS001 - RUSTIC LOVE | B42: 225.95 | C42: 24084.18 | D42: Savannah
A43: STY008 - STYLE 2 FUNK t/a CORPORATE STYLING | B43: 225.94 | C43: 88955.1 | D43: Savannah
A44: EST001 - ESTHE' LEATHER SHOES | B44: 221.76 | C44: 96769.6 | D44: Bianca
A45: CASH - CASH CUSTOMER | B45: 217.84 | C45: 108379.35
A46: PRO015 - PROJECT DYAD | B46: 217.75 | C46: 99439.15 | D46: Bianca
A47: COS001 - TH STEVENS T/A COSY COUCH | B47: 215.62 | C47: 72161.8 | D47: Michelle
A48: GWO001 - G-WORX THREE CC | B48: 210.27 | C48: 84074.85 | D48: Bianca
A49: DON009 - DONKEY LONG TONG (PTY) LTD | B49: 205.2 | C49: 71820 | D49: Bianca
A50: ISL002 - ISLAND HOUSE TRADING 53 (Pty) Ltd t/a | B50: 196.82 | C50: 71271.5 | D50: Melani
A51: KNA002 - KNAP SAK (PTY) LTD | B51: 185.52 | C51: 75574.5 | D51: Savannah
A52: JOY001 - JOY HOLDINGS 123 PTY | B52: 184.32 | C52: 47963.5 | D52: LM
A53: TRU002 - TRUST SHOPFITTERS | B53: 182.23 | C53: 64430.5 | D53: Michelle
A54: BAR003 - E BARONOS LEATHER MANUFACTURERS CC | B54: 180.87 | C54: 71884.6 | D54: Jordan
A55: ZAP001 - ZAPPHIRE UPHOLSTERY | B55: 179.41 | C55: 41401.85 | D55: Savannah
A56: THE051 - THE GREAT BREAK (pty) LTD | B56: 178.43 | C56: 79317.75 | D56: Bianca
A57: ELS001 - EL SOLE HOLDINGS PTY LTD T/A EL SOLE | B57: 177.02 | C57: 69277.9 | D57: Bianca
... A94: MEY001 - MEYER & FERREIRA STIKLAND CC | B94: 78.6 | C94: 27339.35 | D94: Melani
A95: JOI001 - THE JOINERY FASHION CONCEPTS (Pty) Ltd | B95: 73.91 | C95: 29036.15
A96: TRP001 - TRP CAPITAL (PTY) LTD | B96: 73.77 | C96: 25981.85
A97: VER005 - VERSE STUDIO (Pty) Ltd T/A VERSE | B97: 72.53 | C97: 32630.4
A98: HAN009 - THE HANDWORK HUB PTY LTD | B98: 71.56 | C98: 25024.4
A99: DOU002 - DOUBLE BARREL CC | B99: 70.2 | C99: 24217.28
A100: IKU001 - OU HOUT MEUBEL VERVAARDIGERS (PTY) LTD | B100: 68.16 | C100: 15676.8
A101: ALE003 - ALEXIOU LEATHER COUCHES | B101: 67.89 | C101: 17428.95
A102: LHS001 - LHSA T/A LUXE | B102: 67.74 | C102: 45194.12
A103: SLA002 - SLATER AND DUTCH (PTY) LTD | B103: 65.93 | C103: 23700.85
A104: THE053 - THEMBA MAPHUKI T/A LEATHER DESIGNS | B104: 64.62 | C104: 16442.45
A105: STR006 - STRAYZ | B105: 64.33 | C105: 24737.85 | D105: Craig
A106: LOV002 - LOVE LEATHER SA (PTY) LTD | B106: 63.64 | C106: 21705.1
A107: THE018 - THE GRAND LIVING | B107: 61.78 | C107: 22858.6
A108: TRE014 - TREND BESPOKE (PTY) LTD | B108: 61.24 | C108: 22510.7
A109: LED003 - BUMMEL SHOES | B109: 60.95 | C109: 24970.75
A110: OKA001 - OKAPI-LUXURY BAGS ON ACCESSORIES Pty Ltd | B110: 57.88 | C110: 21065.9
A111: EVO001 - EVOTECH TRADING | B111: 57.75 | C111: 15592.5
A112: BEAT01 - BEATUS GENUINE LEATHER | B112: 57.45 | C112: 20689.75
A113: TEP001 - TEPLOV (PTY) LTD T/A TEPLOV BALLET SHOES | B113: 57.12 | C113: 18623
A114: TOP007 - TOPOLANSKY & ASSOCIATES | B114: 56.42 | C114: 21361.7
A115: TAN003 - TAN LEATHER GOODS (PTY) LTD | B115: 54.38 | C115: 19278
A116: SOF010 - SOFA DIVINE | B116: 54.16 | C116: 13722.1
A117: COO001 - HOT SHEET MANUFACTURING CC T/A COOCH | B117: 53.91 | C117: 17790.3
A118: HOF002 - HOFFMANN FURNITURE | B118: 53.48 | C118: 11765.6
A119: BAO002 - BAO-BAGS | B119: 52.83 | C119: 19048.3 | D119: Michelle
A120: LEM009 - LEMY UPHOLSTERER | B120: 52.03 | C120: 13794
A121: ITF001 - IN TOUCH FURNITURE | B121: 51.05 | C121: 18633.25
A122: DCD001 - DC Leather (Pty) Ltd t/a | B122: 50.09 | C122: 28052.35
A123: CAM003 - CAMPBELL ARMOURY (PTY) LTD | B123: 49.71 | C123: 20540.85
A124: LIY001 - LIYAAN LEATHERS | B124: 49.2 | C124: 20844.05 | D124: Michelle
A125: OST001 - OSTRICH & LEATHER TRADING | B125: 48.72 | C125: 19831.75
A126: LEI001 - LEISURE LOUNGE | B126: 48.04 | C126: 14172.6
A127: SLE002 - SLEEPING COUCH & SOFA MANUFACTURERS | B127: 47.64 | C127: 13339.2
A128: SAV003 - SAVIOR BRAND CO. (Pty) Ltd | B128: 46.59 | C128: 17567.75 | D128: Craig
A129: OAK002 - OAK LEATHER | B129: 45.46 | C129: 19059.4
A130: JAR006 - IMVUSA TRADING 451 (PTY) LTD T/A JARMAN | B130: 44.55 | C130: 13365
A131: WIL020 - WILLEBOK LEATHER | B131: 44.46 | C131: 15615.03
A132: AGD001 - A&G DESIGN | B132: 43.73 | C132: 15994.35
A133: FUR006 - FURNITURE FACTORY SHOP | B133: 43.58 | C133: 12202.4
A134: KIT002 - KITTY'S GENUINE LEATHER BOUTIQUE | B134: 43.54 | C134: 15294.15
A135: NIC012 - NICHE BOARD PRODUCTIONS T/A AT URBAN ART | B135: 42.79 | C135: 13321.3
A136: CON001 - CONCORD INTERIORS | B136: 42.3 | C136: 14593.5
A137: JAN020 - JANET FERREIRA INTERIORS | B137: 41.4 | C137: 15732
A138: NEW012 - NEW LIFE UPHOLSTERY | B138: 41.17 | C138: 14495.5
A139: S2Z001 - S2ZERO PTY LTD | B139: 41.15 | C139: 12517.15
A140: HEL002 - HELLO QUALITY (PTY) LTD | B140: 41.12 | C140: 17378.5
... A219: MAN021 - MANUAL MOZAMBIQUE UPHOLSTER | B219: 17.55 | C219: 5265
A220: CRE007 - CREATIVE LEATHER GOODS | B220: 17.42 | C220: 6563.9 | D220: Craig
A221: PAU009 - PAULS AUTO AND AERO TRIM | B221: 17.34 | C221: 4855.2
A222: FIL015 - TAU LEATHER SOUTH AFRICA (PTY) LTD | B222: 17.3 | C222: 7179.5
A223: LEW001 - LEWIS AND MADGE | B223: 16.8 | C223: 5049.7
A224: KER021 - KERF HANDSTITCHED | B224: 16.63 | C224: 6153.1
A225: SIT003 - COMPANY & GOOD | B225: 16.56 | C225: 6578.95
...

Sheet Hannitan
A1: AFRICAN GAMESKIN GROUP (PTY) LTD | Prepared by: African Gameskin
A2: Purchase Items per Supplier : 01/06/2026 to 30/06/2026
B3: Qty | C3: Unit Cost | D3: Total
A4: Supplier : HAN001 - HANNITAN LEATHER CC
A5: Item : AVI001 - AVIATOR WARRIOR | B5: 37.56 | C5: 280 | D5: 10516.8
A6: Item : BWO001 - WOODLAND B PRINT SPICE | B6: 1703.95 | C6: 207 | D6: 352717.65
A7: Item : BWO002 - WOODLAND B PRINT TAN | B7: 2485.45 | C7: 207 | D7: 514488.15
A8: Item : BWO006 - WOODLAND B PRINT GRAPHITE | B8: 681.22 | C8: 207 | D8: 141012.54
A9: Item : CAP002 - CAPE BUFFALO COPPER | B9: 330.06 | C9: 274 | D9: 90436.44
A10: Item : CAP012 - CAPRIVI BRANDY | B10: 568.72 | C10: 187.39035 | D10: 112455.57
A11: Item : CAS007 - CASTROL COCOA MILLED | B11: 1018.77 | C11: 232 | D11: 236354.64
A12: Item : COD001 - CODIAC TAUPE | B12: 739.87 | C12: 207 | D12: 153153.09
A13: Item : DAY002 - DAYTONA ESPRESSO | B13: 407.59 | C13: 292 | D13: 119016.28
A14: Item : DAY011 - DAYTONA TOFFEE | B14: 837.71 | C14: 292 | D14: 244611.32
A15: Item : DIE002 - DIESEL ROSEWOOD | B15: 371.4 | C15: 275 | D15: 102135
A16: Item : DIE004 - DIESEL BLACK | B16: 249.6 | C16: 275 | D16: 68640
... A43: Item : WLS003 - WOODLAND CHARCOAL B | B43: 615.31 | C43: 207 | D43: 127369.17
A44: Total for Supplier : HAN001 - HANNITAN LEATHER CC | B44: =SUM(B5:B43) -> 27484.3 | D44: =SUM(D5:D43) -> 6103468.1
A45: GRAND TOTAL
D46: =+D44/B44 -> 222.07108

Sheet FLW
A1: AFRICAN GAMESKIN GROUP (PTY) LTD | Prepared by: African Gameskin
A2: Purchase Items per Supplier : 01/06/2026 to 30/06/2026
A4: Supplier : TAN001 - FUSION LEATHER WORLD
B5: Qty | C5: Unit Cost | D5: Total
A7: Item : APA001 - APACHE WALNUT | B7: 324.6 | C7: 365 | D7: 118479
A8: Item : ATL007 - ATLANTA TAN | B8: 19.06 | C8: 345 | D8: 6575.7
A9: Item : CAN031 - CANDOR LEMON DROP | B9: 214.7 | C9: 365 | D9: 78365.5
A10: Item : CHI001 - CHICAGO GREEN | B10: 328.45 | C10: 365 | D10: 119884.25
A11: Item : CHI002 - CHICAGO TAN | B11: 304.59 | C11: 364.43465 | D11: 111003.15
A12: Item : COS002 - COSMO DUSTY PINK | B12: 313.03 | C12: 365 | D12: 114255.95
A13: Item : COS003 - COSMO SAGE GREEN | B13: 313.62 | C13: 364.04343 | D13: 114171.3
A14: Item : COS005 - COSMO CHOC | B14: 311.85 | C14: 365 | D14: 113825.25
A15: Item : COW001 - COW SUEDE SPLITS CHOC | B15: 289.2 | C15: 262 | D15: 75770.4
A16: Item : COW002 - COW SUEDE SPLITS BLACK | B16: 314.15 | C16: 262 | D16: 82307.3
A17: Item : COW015 - COW SUEDE CIDER | B17: 202.65 | C17: 252.12607 | D17: 50118
A18: Item : DAL006 - DALLAS CHOC | B18: 23.62 | C18: 345 | D18: 8148.9
... A34: Item : TUS010 - BARCELONA NAVY | B34: 331.92 | C34: 365 | D34: 121150.8
A36: GRAND TOTAL
B37: =SUM(B7:B36) -> 7277.34 | D37: =SUM(D7:D36) -> 2513317.9
D38: =+D37/B37 -> 345.36217

Sheet Customer for the year

Sheet Dashboard Analysis

Sheet Analysis Dashboard
A1: AFRICAN GAMESKIN GROUP - JUNE 2026 DASHBOARD ANALYSIS
A3: KEY PERFORMANCE METRICS | I3: QUICK SUMMARY
A4: Metric | B4: Value | C4: Notes | I4: Total Turnover: | J4: =B5 -> 9605934.8 | L4: Net Profit (YTD): | M4: =B11 -> 1174284.9
A5: Total Turnover | B5: ='Monthly sheet '!D6+'Monthly sheet '!D7 -> 9605934.8 | C5: Local + Exports | I5: Gross Margin: | J5: =B9 -> 0.056603204 | L5: Total Debtors: | M5: =B27 -> 9500331
A6: Local Sales | B6: ='Monthly sheet '!D6 -> 8846029.9 | C6: 92% of turnover | I6: Total Stock: | J6: ='Monthly sheet '!M40 -> 28252762 | L6: Total Creditors: | M6: ='Monthly sheet '!H31 -> 3246489.7
A7: Export Sales | B7: ='Monthly sheet '!D7 -> 759904.9 | C7: 8% of turnover
A8: Gross Profit (June) | B8: ='Monthly sheet '!L21 -> 542952.45
A9: Gross Profit Margin | B9: ='Monthly sheet '!M21 -> 0.056603204 | C9: Below target
A10: Net Profit (June) | B10: ='Monthly sheet '!L24 -> -12544.95 | C10: Loss this month
A11: Net Profit YTD | B11: ='Monthly sheet '!L32 -> 1174284.9 | C11: Positive YTD
A12: YTD Profit Margin | B12: ='Monthly sheet '!M32 -> 0.032801934
A14: SALES BY BRANCH (M2) | F14: Branch Sales Data
A15: Branch | B15: 46174 | C15: 46143 | D15: Change % | F15: Branch | G15: 46174
A16: Durban | B16: ='Monthly sheet '!C18 -> 2362 | C16: ='Monthly sheet '!D18 -> 2702 | D16: =(B16-C16)/C16 -> -0.12583272 | F16: Durban | G16: =B16 -> 2362
A17: JHB | B17: ='Monthly sheet '!C19 -> 9987 | C17: ='Monthly sheet '!D19 -> 9663 | D17: =(B17-C17)/C17 -> 0.03352996 | F17: JHB | G17: =B17 -> 9987
A18: Cape Town | B18: ='Monthly sheet '!C20 -> 15762 | C18: ='Monthly sheet '!D20 -> 14573 | D18: =(B18-C18)/C18 -> 0.08158924 | F18: Cape Town | G18: =B18 -> 15762
A19: TOTAL | B19: =SUM(B16:B18) -> 28111 | C19: =SUM(C16:C18) -> 26938 | D19: =(B19-C19)/C19 -> 0.043544435
A21: DEBTORS AGING ANALYSIS | F21: Debtors Aging Data
A22: Aging Bucket | B22: Amount | C22: % of Total | D22: Risk Level | F22: Aging | G22: Amount
A23: Current | B23: ='Monthly sheet '!H20 -> 5750509.5 | C23: =B23/B27 -> 0.6052957 | D23: Low | F23: Current | G23: =B23 -> 5750509.5
A24: 30 Days | B24: ='Monthly sheet '!H21 -> 2659650.2 | C24: =B24/B27 -> 0.27995342 | D24: Medium | F24: 30 Days | G24: =B24 -> 2659650.2
A25: 60 Days | B25: ='Monthly sheet '!H22 -> 339704.74 | C25: =B25/B27 -> 0.035757148 | D25: High | F25: 60 Days | G25: =B25 -> 339704.74
A26: 90+ Days | B26: ='Monthly sheet '!H23+'Monthly sheet '!H24 -> 750466.57 | C26: =B26/B27 -> 0.078993729 | D26: Critical | F26: 90+ Days | G26: =B26 -> 750466.57
A27: TOTAL | B27: =SUM(B23:B26) -> 9500331 | C27: =SUM(C23:C26) -> 1
A29: STOCK INVENTORY BY LOCATION | F29: Stock Value Data
A30: Location | B30: M2 | C30: Value (R) | D30: % of Total | F30: Location | G30: Value
A31: Cape Town | B31: ='Monthly sheet '!L36 -> 72417 | C31: ='Monthly sheet '!M36 -> 20103816 | D31: =C31/$C$34 -> 0.71156994 | F31: Cape Town | G31: =C31 -> 20103816
A32: JHB | B32: ='Monthly sheet '!L37 -> 26594 | C32: ='Monthly sheet '!M37 -> 6028419 | D32: =C32/$C$34 -> 0.2133745 | F32: JHB | G32: =C32 -> 6028419
A33: Durban | B33: ='Monthly sheet '!L38 -> 3891.47 | C33: ='Monthly sheet '!M38 -> 999058.3 | D33: =C33/$C$34 -> 0.035361438 | F33: Durban | G33: =C33 -> 999058.3
A34: TOTAL | B34: =SUM(B31:B33) -> 102902.47 | C34: ='Monthly sheet '!M40 -> 28252762 | D34: =SUM(D31:D33) -> 0.96030588
A36: TOP 10 CUSTOMERS | F36: Top Customers Data
A37: Rank | B37: Customer | C37: M2 | D37: Value (R) | F37: Customer | G37: Value
A38: 1 | B38: ='Monthly sheet '!B25 -> INSPIRE RENTALS PTY LTD | C38: ='Monthly sheet '!C25 -> 1648.56 | D38: ='Monthly sheet '!D25 -> 400521.1 | F38: INSPIRE RENTALS | G38: =D38 -> 400521.1
A39: 2 | B39: ='Monthly sheet '!B26 -> GH LEATHERS LTD | C39: ='Monthly sheet '!C26 -> 1464.08 | D39: ='Monthly sheet '!D26 -> 677878.46 | F39: GH LEATHERS | G39: =D39 -> 677878.46
A40: 3 | B40: ='Monthly sheet '!B27 -> JULIANA DESIGNS (PTY) LTD | C40: ='Monthly sheet '!C27 -> 1244.83 | D40: ='Monthly sheet '!D27 -> 329879.95 | F40: JULIANA DESIGNS | G40: =D40 -> 329879.95
A41: 4 | B41: ='Monthly sheet '!B28 -> COUCH POTATO | C41: ='Monthly sheet '!C28 -> 856.94 | D41: ='Monthly sheet '!D28 -> 213084.55 | F41: COUCH POTATO | G41: =D41 -> 213084.55
A42: 5 | B42: ='Monthly sheet '!B29 -> INYATHI LOUNGE (PTY) LTD | C42: ='Monthly sheet '!C29 -> 834.04 | D42: ='Monthly sheet '!D29 -> 202000.95 | F42: INYATHI LOUNGE | G42: =D42 -> 202000.95
A43: 6 | B43: ='Monthly sheet '!B30 -> ALWAYS AROUND (PTY) LTD T/A BEESDAM | C43: ='Monthly sheet '!C30 -> 787.17 | D43: ='Monthly sheet '!D30 -> 221597.55 | F43: ALWAYS AROUND | G43: =D43 -> 221597.55
A44: 7 | B44: ='Monthly sheet '!B31 -> LEATHER DIRECT (Pty) Ltd | C44: ='Monthly sheet '!C31 -> 722.42 | D44: ='Monthly sheet '!D31 -> 181422 | F44: LEATHER DIRECT | G44: =D44 -> 181422
A45: 8 | B45: ='Monthly sheet '!B32 -> ROWDY INTERNATIONAL (Pty) Ltd | C45: ='Monthly sheet '!C32 -> 707.48 | D45: ='Monthly sheet '!D32 -> 215960.95 | F45: ROWDY INTL | G45: =D45 -> 215960.95
A46: 9 | B46: ='Monthly sheet '!B33 -> LEATHER DIRECT (Pty) Ltd | C46: ='Monthly sheet '!C33 -> 597.6 | D46: ='Monthly sheet '!D33 -> 148022.8 | F46: LEATHER DIRECT 2 | G46: =D46 -> 148022.8
A47: 10 | B47: ='Monthly sheet '!B34 -> FF CLOTHING GROUP CC | C47: ='Monthly sheet '!C34 -> 583.21 | D47: ='Monthly sheet '!D34 -> 232642.6 | F47: FF CLOTHING | G47: =D47 -> 232642.6
A49: KEY INSIGHTS & OBSERVATIONS
A50: 1. PROFITABILITY CONCERN: June 2026 shows a net loss of R12,545, though YTD remains positive at R1.17M
A51: 2. GROSS MARGIN: At 6%, gross margin is significantly below industry norms (typically 15-25%)
A52: 3. BRANCH PERFORMANCE: Cape Town dominates with 56% of M2 sold, JHB at 35%, Durban at 8%
A53: 4. CUSTOMER CONCENTRATION: Top 10 customers represent 33.6% of sales - moderate risk
A54: 5. DEBTORS RISK: 7.9% (R750K) of debtors are 90+ days overdue - requires collection attention
A55: 6. STOCK LEVELS: R28.3M tied in inventory, Cape Town holding 71% of stock value
A56: 7. SUPPLIER POSITION: 100% of creditors current (no overdue) - healthy supplier relations
A57: 8. INVENTORY BUILD: Purchased 34,762 M2 vs sold 28,112 M2 - building stock levels
A58: 9. MARGIN ANALYSIS: Avg sell price R326/M2 vs purchase R239/M2 = 36% markup
A59: 10. RETURNS: 115 credit notes (5% of sales = R512K) - quality/returns monitoring needed
